{
 "slug": "hotel-hospitality-roofing",
 "taxonomy": "project-types",
 "route": "/project-types/hotel-hospitality-roofing",
 "title": "Hotel and Hospitality Roofing in Provo, UT | Commercial Roofers of Provo",
 "metaDescription": "Hotel and hospitality roofing from downtown Provo to Provo Canyon: guest-comfort insulation, mountain snow-load resorts, low-disruption scheduling.",
 "internalLinks": [
  {
   "anchor": "Apartment and Student Housing Roofs Around BYU and UVU",
   "slug": "multifamily-apartment-roofing",
   "taxonomy": "project-types",
   "href": "/project-types/multifamily-apartment-roofing"
  },
  {
   "anchor": "Office Roofs Between the Silicon Slopes Corridor and Downtown Provo",
   "slug": "office-complex-roofing",
   "taxonomy": "project-types",
   "href": "/project-types/office-complex-roofing"
  },
  {
   "anchor": "Restaurant Roofs Along University Parkway and State Street",
   "slug": "restaurant-standalone-roofing",
   "taxonomy": "project-types",
   "href": "/project-types/restaurant-standalone-roofing"
  },
  {
   "anchor": "Warehouse Roofs Along Geneva Road and the I-15 Industrial Corridor",
   "slug": "warehouse-roofing",
   "taxonomy": "project-types",
   "href": "/project-types/warehouse-roofing"
  },
  {
   "anchor": "Big-Box Roofs Along University Parkway and State Street",
   "slug": "big-box-retail-roofing",
   "taxonomy": "project-types",
   "href": "/project-types/big-box-retail-roofing"
  },
  {
   "anchor": "Concealed-Fastener Panels for Snow-Shedding Roofs Above Provo Canyon",
   "slug": "standing-seam-metal-roofing",
   "taxonomy": "services",
   "href": "/services/standing-seam-metal-roofing"
  },
  {
   "anchor": "Camp Floyd's Historic Roofs and Fairfield's Ranches Need Two Different Approaches",
   "slug": "fairfield",
   "taxonomy": "locations",
   "href": "/locations/fairfield"
  },
  {
   "anchor": "Roofs Designed Around What's Running Underneath Them",
   "slug": "manufacturing-operators",
   "taxonomy": "industries",
   "href": "/industries/manufacturing-operators"
  }
 ],
 "html": "<h1>Hotel Roofs From Downtown Provo to the Resort Properties Up the Canyon</h1>\n<p>Hospitality buildings in this valley range from hotels clustered near Provo Towne Centre and the Riverwoods district down to resort lodges tucked into Provo Canyon, each carrying a different set of pressures on the roof above them. A downtown business hotel and a mountain resort property built for heavy snow country need very different approaches, even when the membrane system underneath looks similar.</p>\n<h2>A Hotel Never Fully Closes, and Neither Does the Project Around It</h2>\n<p>Hotels run at some level of occupancy every night of the year, which means a roof project has to plan around guests sleeping directly below the work zone rather than an empty building. We sequence tear-off wing by wing or floor by floor, coordinating with hotel management on which rooms are booked and which sections can be blocked from reservations during active work, keeping noise and staging away from occupied guest floors whenever possible.</p>\n<p>Daytime housekeeping and turnover schedules add another layer of coordination, since staging equipment near a guest entrance or pool deck during peak checkout and check-in hours creates a first impression problem for the property, not merely a logistics one.</p>\n<h2>Mountain Snow Load at Resort Properties Up the Canyon</h2>\n<p>Resort and lodge properties up Provo Canyon sit at significantly higher elevation and see far heavier snow loads than the valley floor, which changes both the structural requirements and the maintenance pattern for these roofs. Snow retention, drift management around dormers and roof transitions, and ice dam prevention all take on more weight at these elevations than they would for a downtown hotel property.</p>\n<p>We check insulation continuity carefully on these mountain properties, since ice damming almost always traces back to interior heat escaping through a gap in the roof assembly and melting snow unevenly, refreezing at the eave in a pattern that damages both the roof and anything below it.</p>\n<h2>Guest Comfort Depends on Roof Performance More Than Owners Realize</h2>\n<p>Top-floor guest rooms feel roof performance directly, through both temperature swings and, in bad cases, noise from HVAC units working overtime to compensate for heat loss or gain through the deck. We evaluate insulation condition on hotel roofs with guest comfort as a specific line item, not merely an energy cost consideration, since a guest complaint about a hot or cold top-floor room often traces straight back to the roof.</p>\n<p>Reflective membrane surfaces help on the summer side of that equation, cutting surface heat that would otherwise radiate down into top-floor rooms and push HVAC systems harder during check-in and check-out hours when demand on those systems already peaks.</p>\n<ul>\n<li>Downtown and business-district hotels</li>\n<li>Extended-stay and residence-style hotel properties</li>\n<li>Highway and interstate-adjacent hotel properties</li>\n<li>Resort lodges and mountain hospitality properties</li>\n<li>Banquet and conference center buildings attached to hotels</li>\n<li>Hotel properties with rooftop pool or amenity decks</li>\n</ul>\n<h2>Rooftop Amenity Decks and Mechanical Screening</h2>\n<p>Hotels with rooftop pools, bars, or amenity decks carry roof considerations a standard building doesn't, with waterproofing beneath a pool deck and drainage engineered for both stormwater and pool overflow. We treat these amenity roof sections as their own category during inspections, since the failure modes and repair approach for a trafficked amenity deck differ meaningfully from the surrounding low-slope roof field.</p>\n<p>Mechanical screening around rooftop HVAC and elevator equipment also needs to hold up visually as well as functionally on a hotel, since guests and event attendees sometimes have direct sightlines to rooftop areas from upper floors or nearby buildings.</p>\n<h2>Banquet and Conference Space Roofs Take a Different Kind of Punishment</h2>\n<p>Hotels with attached banquet halls and conference centers often carry a wider, taller roof span over that portion of the building than the guest room towers, and that span brings its own snow load and drainage considerations separate from the rest of the property. Event schedules add another wrinkle, since a wedding or conference booked months in advance leaves very little flexibility for shifting a roof project once it's on the calendar.</p>\n<p>We work with hotel sales and events staff on locking in roof project windows well ahead of the property's own booking calendar, since a banquet space roof needing attention during a fully booked wedding season creates a scheduling conflict that's better solved months out than the week of an event.</p>\n<h2>Emergency Response for a Property That Can't Turn Away Guests</h2>\n<p>A roof leak during an active storm is a bigger problem for a hotel than for almost any other commercial building type, since displaced guests and damaged rooms translate directly into lost revenue and refunded stays. We prioritize emergency tarping and dry-in response for hotel properties specifically because of that guest-facing exposure, working to protect affected rooms and get them back in rotation as fast as the situation allows.</p>\n<p>We also coordinate directly with hotel engineering staff during storm response, since most properties have their own internal escalation process for guest room issues that our crew needs to work alongside rather than around.</p>\n<h2>Questions Hotel Owners and General Managers Ask Us</h2>\n<h3>Can you work on our roof without blocking guest rooms from reservations?</h3>\n<p>We sequence work wing by wing or floor by floor and coordinate with your reservations team on which sections need to stay clear during active work.</p>\n<h3>How is a mountain resort roof different from a valley hotel roof?</h3>\n<p>Elevation up Provo Canyon brings heavier snow load and more aggressive ice damming risk, which changes both structural requirements and insulation priorities.</p>\n<h3>Does roof condition really affect guest comfort in top-floor rooms?</h3>\n<p>Yes, insulation gaps and reduced membrane reflectivity show up directly as temperature complaints and overworked HVAC units in top-floor rooms.</p>\n<h3>Do you handle rooftop pool decks differently than the main roof?</h3>\n<p>Yes, we treat amenity decks as their own category, since waterproofing and drainage needs differ from the surrounding low-slope field.</p>\n<h3>How fast can you respond to a leak during an active storm?</h3>\n<p>We prioritize emergency tarping and dry-in for hotel properties specifically, working to protect affected rooms and restore them to rotation quickly.</p>",
 "image": "/images/project-types/hotel-hospitality-roofing-commercial-roofers-provo-ut.webp"
}
